simple_otel_py/__init__.py
simple_otel_py/simple_otel.py
simple_otel_py-0.0.9.dist-info/LICENSE
simple_otel_py-0.0.9.dist-info/METADATA
simple_otel_py-0.0.9.dist-info/WHEEL
simple_otel_py-0.0.9.dist-info/top_level.txt
simple_otel_py-0.0.9.dist-info/RECORD
